selecta/__init__.py
selecta/commands/__init__.py
selecta/commands/selecta_add_keybinding.py
selecta-0.2.1.dist-info/LICENSE.txt
selecta-0.2.1.dist-info/METADATA
selecta-0.2.1.dist-info/WHEEL
selecta-0.2.1.dist-info/entry_points.txt
selecta-0.2.1.dist-info/top_level.txt
selecta-0.2.1.dist-info/RECORD
