Metadata-Version: 2.1
Name: selecta
Version: 0.2.1
Summary: Interactively select an entry from your bash/zsh history.
Author-email: Thomas Schüßler <vindolin@gmail.com>
License: The MIT License (MIT)
Project-URL: Homepage, https://github.com/vindolin/selecta
Project-URL: Changelog, https://github.com/vindolin/selecta/blob/master/CHANGELOG.md
Keywords: bash,zsh,curses,history
Classifier: Development Status :: 5 - Production/Stable
Classifier: Environment :: Console :: Curses
Classifier: Programming Language :: Python :: 3
Classifier: Operating System :: MacOS
Classifier: Operating System :: POSIX :: Linux
Requires-Python: >=3.9
License-File: LICENSE.txt
Requires-Dist: urwid >=2.2.0
